cognitive/__init__.py
cognitive/agent.py
cognitive/logics.py
uicognitive_sdk-1.0.0.dist-info/LICENSE
uicognitive_sdk-1.0.0.dist-info/METADATA
uicognitive_sdk-1.0.0.dist-info/WHEEL
uicognitive_sdk-1.0.0.dist-info/top_level.txt
uicognitive_sdk-1.0.0.dist-info/RECORD
