Metadata-Version: 2.1
Name: uicognitive-sdk
Version: 1.0.0
Summary: Python SDK for Azure Cognitive Services
Home-page: https://jjnanthakumar.github.io
Author: Nanthakumar J J
Author-email: nanthakumar.j@ubtiinc.com
License: GNU Lesser General Public License v3 (LGPLv3)
Platform: UNKNOWN
Classifier: Intended Audience :: Developers
Classifier: License :: OSI Approved :: BSD License
Classifier: Operating System :: OS Independent
Classifier: Programming Language :: Python
Classifier: Programming Language :: Python :: 3
Classifier: Programming Language :: Python :: 3 :: Only
Classifier: Programming Language :: Python :: 3.6
Classifier: Programming Language :: Python :: 3.7
Classifier: Programming Language :: Python :: 3.8
Classifier: Programming Language :: Python :: 3.9
Classifier: Topic :: Internet :: WWW/HTTP
Classifier: Topic :: Internet :: WWW/HTTP :: Dynamic Content
Requires-Python: >=3.6
License-File: LICENSE
Requires-Dist: requests
